pysteamcmd/__init__.py
pysteamcmd/steamcmd.py
pysteamcmd/tests/__init__.py
pysteamcmd-0.3.0.dist-info/LICENSE
pysteamcmd-0.3.0.dist-info/METADATA
pysteamcmd-0.3.0.dist-info/WHEEL
pysteamcmd-0.3.0.dist-info/top_level.txt
pysteamcmd-0.3.0.dist-info/RECORD
