Metadata-Version: 2.1
Name: pysteamcmd
Version: 0.3.0
Summary: Python package to install and utilize steamcmd
Home-page: https://github.com/f0rkz/pysteamcmd
Author: f0rkz
Author-email: f0rkz@f0rkznet.net
License: UNKNOWN
Project-URL: Bug Tracker, https://github.com/f0rkz/pysteamcmd/issues
Platform: UNKNOWN
Classifier: Programming Language :: Python :: 3
Classifier: License :: OSI Approved :: MIT License
Classifier: Operating System :: OS Independent
Requires-Python: >=3.6
License-File: LICENSE
